setup.py
ncutils/__init__.py
ncutils/base.py
ncutils/mylist.py
ncutils/ncsh.py
ncutils/network.py
ncutils/recipes.py
ncutils/search.py
ncutils/util.py
ncutils/video.py
ncutils/watch.py
ncutils.egg-info/PKG-INFO
ncutils.egg-info/SOURCES.txt
ncutils.egg-info/dependency_links.txt
ncutils.egg-info/entry_points.txt
ncutils.egg-info/top_level.txt