Metadata-Version: 1.0
Name: ncutils
Version: 0.3.0
Summary: niconico douga module
Home-page: https://github.com/sakamotomsh/ncutils
Author: sakamotomsh
Author-email: sakamotomsh@lolloo.net
License: BSD
Platform: UNKNOWN
Classifier: Development Status :: 3 - Alpha
Classifier: Environment :: Console
Classifier: Intended Audience :: Developers
Classifier: License :: OSI Approved :: BSD License
Classifier: Operating System :: OS Independent
Classifier: Programming Language :: Python
Classifier: Programming Language :: Python :: 2.7
Classifier: Topic :: Internet :: WWW/HTTP :: Dynamic Content
Classifier: Topic :: Utilities
